server_code/__init__.py
server_code/server_reports.py
server_code/server_surveys.py
tests/__init__.py
tests/test_funcs.py
OpenQuestion-0.1.1.dist-info/LICENSE
OpenQuestion-0.1.1.dist-info/METADATA
OpenQuestion-0.1.1.dist-info/WHEEL
OpenQuestion-0.1.1.dist-info/top_level.txt
OpenQuestion-0.1.1.dist-info/RECORD
