Metadata-Version: 2.1
Name: OpenQuestion
Version: 0.1.1
Summary: An open source survey platform written in Python.
Home-page: https://github.com/Alcampopiano/OpenQuestion
Author: Allan Campopiano
Author-email: campopianoa@hcdsb.org
License: BSD 3-clause
Classifier: Development Status :: 4 - Beta
Classifier: Environment :: Console
Classifier: Intended Audience :: Science/Research
Classifier: License :: OSI Approved :: BSD License
Classifier: Natural Language :: English
Classifier: Programming Language :: Python :: 3.6
Classifier: Programming Language :: Python :: 3.7
Classifier: Programming Language :: Python :: 3.8
Classifier: Programming Language :: Python :: 3.9
Classifier: Programming Language :: Python :: 3.10
Requires-Python: >=3.6
License-File: LICENSE
Requires-Dist: pandas (==1.4.3)
Requires-Dist: numpy (==1.23.1)
Requires-Dist: anvil-app-server (==1.7.3)
Requires-Dist: mistune (==2.0.4)
Requires-Dist: anvil-uplink (==0.3.42)
Requires-Dist: bcrypt (==3.2.2)
